[
  {
    "传送点名称": "天穹巨鲸",
    "传送节点": "xx",
    "需求条件": "$玩家等级 >= 20",
    "图片资源路径": "sandboxId://FlyUi/迷你界面/传送UI/天穹巨鲸.png",
    "变量表达公式": "$玩家等级 >= 20 && $任务进度 >= 5"
  },
  {
    "传送点名称": "樱花海洋",
    "传送节点": "ss",
    "需求条件": "$玩家等级 >= 40",
    "图片资源路径": "sandboxId://FlyUi/迷你界面/传送UI/樱花海洋.png",
    "变量表达公式": "$玩家等级 >= 40 && $樱花岛声望 >= 100"
  },
  {
    "传送点名称": "科技空岛",
    "传送节点": "60",
    "需求条件": "$玩家等级 >= 60",
    "图片资源路径": "sandboxId://FlyUi/迷你界面/传送UI/科技空岛.png",
    "变量表达公式": "$玩家等级 >= 60 && $科技点数 >= 500"
  }
]