[
  {
    "宠物名称": "纸箱喵喵",
    "抽奖区域": "高级高级",
    "品级": "SSR",
    "图片": "",
    "图片资源": "sandboxId://FlyUi/迷你界面/宠物立绘/纸箱喵喵.png",
    "模型": "resId&usev2=1://409925266970267655",
    "动画": "resId&usev2=1://416003064827076611",
    "加成_百分比_训练加成": "S_LVL*1200"
  },
  {
    "宠物名称": "呆呆星宝",
    "抽奖区域": "高级高级",
    "品级": "SR",
    "图片": "",
    "图片资源": "sandboxId://FlyUi/迷你界面/宠物立绘/呆呆星宝.png",
    "模型": "resId&usev2=1://409929753839554566",
    "动画": "resId&usev2=1://416003064827076611",
    "加成_百分比_训练加成": "S_LVL*900"
  },
  {
    "宠物名称": "小白咕咕",
    "抽奖区域": "高级高级",
    "品级": "R",
    "图片": "",
    "图片资源": "sandboxId://FlyUi/迷你界面/宠物立绘/小白咕咕.png",
    "模型": "resId&usev2=1://409930554364416002",
    "动画": "resId&usev2=1://416003064827076611",
    "加成_百分比_训练加成": "S_LVL*600"
  },
  {
    "宠物名称": "咕噜星宝",
    "抽奖区域": "高级高级",
    "品级": "N",
    "图片": "",
    "图片资源": "sandboxId://FlyUi/迷你界面/宠物立绘/咕噜星宝.png",
    "模型": "resId&usev2=1://409931224714858502",
    "动画": "resId&usev2=1://416003064827076611",
    "加成_百分比_训练加成": "S_LVL*300"
  },
  {
    "宠物名称": "熊熊酷仔",
    "抽奖区域": "高级中级",
    "品级": "SSR",
    "图片": "",
    "图片资源": "sandboxId://FlyUi/迷你界面/宠物立绘/熊熊酷仔.png",
    "模型": "resId&usev2=1://409931794456530944",
    "动画": "resId&usev2=1://416003064827076611",
    "加成_百分比_训练加成": "S_LVL*850"
  },
  {
    "宠物名称": "狐狸豆豆",
    "抽奖区域": "高级中级",
    "品级": "SR",
    "图片": "",
    "图片资源": "sandboxId://FlyUi/迷你界面/宠物立绘/狐狸豆豆.png",
    "模型": "resId&usev2=1://409925400383053831",
    "动画": "resId&usev2=1://416003064827076611",
    "加成_百分比_训练加成": "S_LVL*580"
  },
  {
    "宠物名称": "抱抱熊宝",
    "抽奖区域": "高级中级",
    "品级": "R",
    "图片": "",
    "图片资源": "sandboxId://FlyUi/迷你界面/宠物立绘/抱抱熊宝.png",
    "模型": "resId&usev2=1://409931687518920706",
    "动画": "resId&usev2=1://416003064827076611",
    "加成_百分比_训练加成": "S_LVL*320"
  },
  {
    "宠物名称": "白团团兔",
    "抽奖区域": "高级中级",
    "品级": "N",
    "图片": "",
    "图片资源": "sandboxId://FlyUi/迷你界面/宠物立绘/白团团兔.png",
    "模型": "resId&usev2=1://409929876380704770",
    "动画": "resId&usev2=1://416003064827076611",
    "加成_百分比_训练加成": "S_LVL*150"
  },
  {
    "宠物名称": "蓝蓝喵星",
    "抽奖区域": "高级初级",
    "品级": "SSR",
    "图片": "",
    "图片资源": "sandboxId://FlyUi/迷你界面/宠物立绘/蓝蓝喵星.png",
    "模型": "resId&usev2=1://409931835615236104",
    "动画": "resId&usev2=1://416003064827076611",
    "加成_百分比_训练加成": "S_LVL*500"
  },
  {
    "宠物名称": "嘟嘟小魔",
    "抽奖区域": "高级初级",
    "品级": "SR",
    "图片": "",
    "图片资源": "sandboxId://FlyUi/迷你界面/宠物立绘/嘟嘟小魔.png",
    "模型": "resId&usev2=1://409925361241444358",
    "动画": "resId&usev2=1://416003064827076611",
    "加成_百分比_训练加成": "S_LVL*280"
  },
  {
    "宠物名称": "立耳喵团",
    "抽奖区域": "高级初级",
    "品级": "R",
    "图片": "",
    "图片资源": "sandboxId://FlyUi/迷你界面/宠物立绘/立耳喵团.png",
    "模型": "resId&usev2=1://409929916024901636",
    "动画": "resId&usev2=1://416003064827076611",
    "加成_百分比_训练加成": "S_LVL*120"
  },
  {
    "宠物名称": "金团团狗",
    "抽奖区域": "高级初级",
    "品级": "N",
    "图片": "",
    "图片资源": "sandboxId://FlyUi/迷你界面/宠物立绘/金团团狗.png",
    "模型": "resId&usev2=1://409929968118157320",
    "动画": "resId&usev2=1://416003064827076611",
    "加成_百分比_训练加成": "S_LVL*50"
  },
  {
    "宠物名称": "团团陛下",
    "抽奖区域": "中级高级",
    "品级": "SSR",
    "图片": "",
    "图片资源": "sandboxId://FlyUi/迷你界面/宠物立绘/团团陛下.png",
    "模型": "resId&usev2=1://409925440488988677",
    "动画": "resId&usev2=1://416003064827076611",
    "加成_百分比_训练加成": "S_LVL*230"
  },
  {
    "宠物名称": "呆萌小啾",
    "抽奖区域": "中级高级",
    "品级": "SR",
    "图片": "",
    "图片资源": "sandboxId://FlyUi/迷你界面/宠物立绘/呆萌小啾.png",
    "模型": "resId&usev2=1://409931725338595330",
    "动画": "resId&usev2=1://416003064827076611",
    "加成_百分比_训练加成": "S_LVL*170"
  },
  {
    "宠物名称": "粉团团猪",
    "抽奖区域": "中级高级",
    "品级": "R",
    "图片": "",
    "图片资源": "sandboxId://FlyUi/迷你界面/宠物立绘/粉团团猪.png",
    "模型": "resId&usev2=1://409930016272961537",
    "动画": "resId&usev2=1://416003064827076611",
    "加成_百分比_训练加成": "S_LVL*120"
  },
  {
    "宠物名称": "棕团团熊",
    "抽奖区域": "中级高级",
    "品级": "N",
    "图片": "",
    "图片资源": "sandboxId://FlyUi/迷你界面/宠物立绘/棕团团熊.png",
    "模型": "resId&usev2=1://409930108199886855",
    "动画": "resId&usev2=1://416003064827076611",
    "加成_百分比_训练加成": "S_LVL*60"
  },
  {
    "宠物名称": "汪汪警长",
    "抽奖区域": "中级中级",
    "品级": "SSR",
    "图片": "",
    "图片资源": "sandboxId://FlyUi/迷你界面/宠物立绘/汪汪警长.png",
    "模型": "resId&usev2=1://409925967914328065",
    "动画": "resId&usev2=1://416003064827076611",
    "加成_百分比_训练加成": "S_LVL*180"
  },
  {
    "宠物名称": "熊熊灰灰",
    "抽奖区域": "中级中级",
    "品级": "SR",
    "图片": "",
    "图片资源": "sandboxId://FlyUi/迷你界面/宠物立绘/熊熊灰灰.png",
    "模型": "resId&usev2=1://409931868016234503",
    "动画": "resId&usev2=1://416003064827076611",
    "加成_百分比_训练加成": "S_LVL*130"
  },
  {
    "宠物名称": "橙团团蝶",
    "抽奖区域": "中级中级",
    "品级": "R",
    "图片": "",
    "图片资源": "sandboxId://FlyUi/迷你界面/宠物立绘/橙团团蝶.png",
    "模型": "resId&usev2=1://409930362936381447",
    "动画": "resId&usev2=1://416003064827076611",
    "加成_百分比_训练加成": "S_LVL*70"
  },
  {
    "宠物名称": "开开星人",
    "抽奖区域": "中级中级",
    "品级": "N",
    "图片": "",
    "图片资源": "sandboxId://FlyUi/迷你界面/宠物立绘/开开星人.png",
    "模型": "resId&usev2=1://409930885466968073",
    "动画": "resId&usev2=1://416003064827076611",
    "加成_百分比_训练加成": "S_LVL*35"
  },
  {
    "宠物名称": "橘萌小狐",
    "抽奖区域": "中级初级",
    "品级": "SSR",
    "图片": "",
    "图片资源": "sandboxId://FlyUi/迷你界面/宠物立绘/橘萌小狐.png",
    "模型": "resId&usev2=1://409926647164719109",
    "动画": "resId&usev2=1://416003064827076611",
    "加成_百分比_训练加成": "S_LVL*90"
  },
  {
    "宠物名称": "银翼天使",
    "抽奖区域": "中级初级",
    "品级": "SR",
    "图片": "",
    "图片资源": "sandboxId://FlyUi/迷你界面/宠物立绘/银翼天使.png",
    "模型": "resId&usev2=1://409925936050200576",
    "动画": "resId&usev2=1://416003064827076611",
    "加成_百分比_训练加成": "S_LVL*60"
  },
  {
    "宠物名称": "方团虫宝",
    "抽奖区域": "中级初级",
    "品级": "R",
    "图片": "",
    "图片资源": "sandboxId://FlyUi/迷你界面/宠物立绘/方团虫宝.png",
    "模型": "resId&usev2=1://409931080980254725",
    "动画": "resId&usev2=1://416003064827076611",
    "加成_百分比_训练加成": "S_LVL*28"
  },
  {
    "宠物名称": "团团海豹",
    "抽奖区域": "中级初级",
    "品级": "N",
    "图片": "",
    "图片资源": "sandboxId://FlyUi/迷你界面/宠物立绘/团团海豹.png",
    "模型": "resId&usev2=1://409931080980254725",
    "动画": "resId&usev2=1://416003064827076611",
    "加成_百分比_训练加成": "S_LVL*12"
  },
  {
    "宠物名称": "咩咩糖糖",
    "抽奖区域": "初级高级",
    "品级": "SSR",
    "图片": "",
    "图片资源": "sandboxId://FlyUi/迷你界面/宠物立绘/咩咩糖糖.png",
    "模型": "resId&usev2=1://409926684124925959",
    "动画": "resId&usev2=1://416003064827076611",
    "加成_百分比_训练加成": "S_LVL*50"
  },
  {
    "宠物名称": "雪灵咕咕",
    "抽奖区域": "初级高级",
    "品级": "SR",
    "图片": "",
    "图片资源": "sandboxId://FlyUi/迷你界面/宠物立绘/雪灵咕咕.png",
    "模型": "resId&usev2=1://409926719734566916",
    "动画": "resId&usev2=1://416003064827076611",
    "加成_百分比_训练加成": "S_LVL*28"
  },
  {
    "宠物名称": "蓝蓝小鱼",
    "抽奖区域": "初级高级",
    "品级": "R",
    "图片": "",
    "图片资源": "sandboxId://FlyUi/迷你界面/宠物立绘/蓝蓝小鱼.png",
    "模型": "resId&usev2=1://409931129428660225",
    "动画": "resId&usev2=1://416003064827076611",
    "加成_百分比_训练加成": "S_LVL*10"
  },
  {
    "宠物名称": "智勇小鲨",
    "抽奖区域": "初级高级",
    "品级": "N",
    "图片": "",
    "图片资源": "sandboxId://FlyUi/迷你界面/宠物立绘/智勇小鲨.png",
    "模型": "resId&usev2=1://409931280121614338",
    "动画": "resId&usev2=1://416003064827076611",
    "加成_百分比_训练加成": "S_LVL*7"
  },
  {
    "宠物名称": "南瓜咔咔",
    "抽奖区域": "初级中级",
    "品级": "SSR",
    "图片": "",
    "图片资源": "sandboxId://FlyUi/迷你界面/宠物立绘/南瓜咔咔.png",
    "模型": "resId&usev2=1://409926758309580800",
    "动画": "resId&usev2=1://416003064827076611",
    "加成_百分比_训练加成": "S_LVL*32"
  },
  {
    "宠物名称": "捣蛋喵灵",
    "抽奖区域": "初级中级",
    "品级": "SR",
    "图片": "",
    "图片资源": "sandboxId://FlyUi/迷你界面/宠物立绘/捣蛋喵灵.png",
    "模型": "resId&usev2=1://409926799636058119",
    "动画": "resId&usev2=1://416003064827076611",
    "加成_百分比_训练加成": "S_LVL*18"
  },
  {
    "宠物名称": "幽紫灯灯",
    "抽奖区域": "初级中级",
    "品级": "R",
    "图片": "",
    "图片资源": "sandboxId://FlyUi/迷你界面/宠物立绘/幽紫灯灯.png",
    "模型": "resId&usev2=1://409931376523862016",
    "动画": "resId&usev2=1://416003064827076611",
    "加成_百分比_训练加成": "S_LVL*8"
  },
  {
    "宠物名称": "兔兔小灵",
    "抽奖区域": "初级中级",
    "品级": "N",
    "图片": "",
    "图片资源": "sandboxId://FlyUi/迷你界面/宠物立绘/兔兔小灵.png",
    "模型": "resId&usev2=1://409931376523862016",
    "动画": "resId&usev2=1://416003064827076611",
    "加成_百分比_训练加成": "S_LVL*3.5"
  },
  {
    "宠物名称": "橘宝喵喵",
    "抽奖区域": "初级初级",
    "品级": "SSR",
    "图片": "",
    "图片资源": "sandboxId://FlyUi/迷你界面/宠物立绘/橘宝喵喵.png",
    "模型": "resId&usev2=1://409929811582902278",
    "动画": "resId&usev2=1://416003064827076611",
    "加成_百分比_训练加成": "S_LVL*15"
  },
  {
    "宠物名称": "喵格灵灵",
    "抽奖区域": "初级初级",
    "品级": "SR",
    "图片": "",
    "图片资源": "sandboxId://FlyUi/迷你界面/宠物立绘/喵格灵灵.png",
    "模型": "resId&usev2=1://409929841911914500",
    "动画": "resId&usev2=1://416003064827076611",
    "加成_百分比_训练加成": "S_LVL*6.5"
  },
  {
    "宠物名称": "飘飘小灵",
    "抽奖区域": "初级初级",
    "品级": "R",
    "图片": "",
    "图片资源": "sandboxId://FlyUi/迷你界面/宠物立绘/飘飘小灵.png",
    "模型": "resId&usev2=1://409931424816713728",
    "动画": "resId&usev2=1://416003064827076611",
    "加成_百分比_训练加成": "S_LVL*2.8"
  },
  {
    "宠物名称": "呆萌小幽",
    "抽奖区域": "初级初级",
    "品级": "N",
    "图片": "",
    "图片资源": "sandboxId://FlyUi/迷你界面/宠物立绘/呆萌小幽.png",
    "模型": "resId&usev2=1://409931468848517128",
    "动画": "resId&usev2=1://416003064827076611",
    "加成_百分比_训练加成": "S_LVL*1.3"
  }
]